pytest_keep_together/__init__.py
pytest_keep_together/pytest_plugin.py
pytest_keep_together-1.0.1.dist-info/METADATA
pytest_keep_together-1.0.1.dist-info/WHEEL
pytest_keep_together-1.0.1.dist-info/entry_points.txt
pytest_keep_together-1.0.1.dist-info/licenses/LICENSE
pytest_keep_together-1.0.1.dist-info/RECORD
