Metadata-Version: 2.1
Name: pytest-keep-together
Version: 1.0.1
Summary: Pytest plugin to customize test ordering by running all 'related' tests together
Project-URL: Homepage, https://github.com/hugo-viana/pytest-keep-together
Project-URL: Bug Tracker, https://github.com/hugo-viana/pytest-keep-together/issues
Author-email: Hugo Viana <hugosemianoviana@gmail.com>
License-File: LICENSE
Classifier: Development Status :: 5 - Production/Stable
Classifier: Framework :: Pytest
Classifier: Intended Audience :: Developers
Classifier: License :: OSI Approved :: MIT License
Classifier: Operating System :: OS Independent
Classifier: Programming Language :: Python :: 3
Classifier: Topic :: Software Development
Requires-Python: >=3.7
Requires-Dist: pytest
